{
  "code_word": {
    "type": "freeform",
    "selections": "text",
    "question": "Enter a code word.",
    "choices": null,
    "tips": null,
    "branches": null
  },

  "temp_shelter": {
    "type": "freeform",
    "selections": "text",
    "question": "Enter a temporary shelter.",
    "choices": null,
    "tips": null,
    "branches": null
  },

  "legal_order": {
    "type": "freeform",
    "selections": "text",
    "question": "Enter a legal order.",
    "choices": null,
    "tips": null,
    "branches": null
  },

  "equipment": {
    "type": "freeform",
    "selections": "text",
    "question": "Enter an equipment.",
    "choices": null,
    "tips": null,
    "branches": null
  },


  "abuse_type": {
    "type": "choices",
    "selections": 4,
    "question": "Which form(s) of abuse are you experiencing?",
    "choices": ["Physical", "Emotional", "Financial", "Other"],
    "tips": {
      "type": "template",
      "template": "If you face {abuse_type} abuse, remember you don't have to face it alone. Reach out to your emergency contact right away."
    },
    "branches": null
  },

  "logging_incidents": {
    "type": "choices",
    "selections": 1,
    "question": "Are you recording the incidents (dates, times, details)?",
    "choices": ["Yes", "No"],
    "tips": {
      "type": "per_choice",
      "data": {
        "Yes": "Log each incident (date, time, and a brief note) so you have clear records if needed later.",
        "No": "Even brief notes on your phone can be helpful. Start logging today."
      }
    },
    "branches": null
  },

  "contact_name": {
    "type": "freeform",
    "selections": "text",
    "question": "Name one person you can call immediately in an emergency.",
    "choices": null,
    "tips": {
      "type": "template",
      "template": "Save {contact_name} in your phone under a code-word so you can quietly call them when you need help."
    },
    "branches": null
  },

  "leave_timing": {
    "type": "freeform",
    "selections": "date",
    "question": "When do you plan to leave?",
    "choices": null,
    "tips": {
      "type": "template",
      "template": "Set a real target {leave_timing} and pack one essential item each day until you're ready."
    },
    "branches": null
  },

  "essentials": {
    "type": "choices",
    "selections": 1,
    "question": "Do you have a go-bag pack with essentials?",
    "choices": ["Yes", "No"],
    "tips": {
      "type": "per_choice",
      "data": {
        "Yes": "Great! Keep your go bag in a hidden spot so you can grab it quickly",
        "No": "Pack a simple go-bag today with essentials like your ID, some cash, and a charger."
      }
    },
    "branches": null
  },

  "money_location": {
    "type": "freeform",
    "selections": "text",
    "question": "Where do you keep emergency cash or cards?",
    "choices": ["Closet, Pillow, Drawer"],
    "tips": {
      "type": "template",
      "template": "Stash some cash and a spare card in {money_location}, a spot your partner won't suspect."
    },
    "branches": null
  },

  "safe_house": {
    "type": "choices",
    "selections": 1,
    "question": "Have you identified a safe place to stay?",
    "choices": ["Yes", "No"],
    "tips": {
      "type": "per_choice",
      "data": {
        "Yes": "Make sure {temp_shelter} knows you may arrive unexpectedly and how to contact you.",
        "No": "Reach out to Victim Services Toronto or a trusted friend now to secure a shelter option before you leave."
      }
    },
    "branches": {
      "Yes": ["temp_shelter"]
    }
  },

  "contact": {
    "type": "choices",
    "selections": 1,
    "question": "Has the abuser continued any contact?",
    "choices": ["Yes", "No"],
    "tips": {
      "type": "per_choice",
      "data": {
        "Yes": "Since you've heard from them, stay vigilant and keep your protection order handy if you have one.",
        "No": "Even without contact, keep your doors locked and your phone on in case you need to call 911."
      }
    },
    "branches": null
  },

  "protection": {
    "type": "choices",
    "selections": 1,
    "question": "Do you have a protection order?",
    "choices": ["Yes", "No"],
    "tips": {
      "type": "per_choice",
      "data": {
        "Yes": "Carry your {legal_order} at all times and share copies with anyone who needs to know.",
        "No": "Consider applying for a protection order; it can help deter unwanted contact."
      }
    },
    "branches": {
      "Yes": ["legal_order"]
    }
  },

  "safety": {
    "type": "choices",
    "selections": 1,
    "question": "Are you using any safety tools (cameras, door alarms)?",
    "choices": ["Yes", "No"],
    "tips": {
      "type": "per_choice",
      "data": {
        "Yes": "Make sure you're {equipment} is in working order and placed where you'll notice it.",
        "No": "Consider installing a simple door alarm or camera to alert you to unexpected entry."
      }
    },
    "branches": {
      "Yes": ["equipment"]
    }
  }
}
